setup.py
salure_helpers/all_solutions/__init__.py
salure_helpers/all_solutions/all_solutions.py
salure_helpers_all_solutions.egg-info/PKG-INFO
salure_helpers_all_solutions.egg-info/SOURCES.txt
salure_helpers_all_solutions.egg-info/dependency_links.txt
salure_helpers_all_solutions.egg-info/not-zip-safe
salure_helpers_all_solutions.egg-info/requires.txt
salure_helpers_all_solutions.egg-info/top_level.txt