Metadata-Version: 1.0
Name: salure-helpers-all-solutions
Version: 1.0.2
Summary: All Solutions wrapper from Salure
Home-page: UNKNOWN
Author: D&A Salure
Author-email: support@salureconnnect.com
License: Salure License
Platform: UNKNOWN
